HistoricalEarningsData/__init__.py
HistoricalEarningsData/earnings_data.py
HistoricalEarningsData/data/aggregated_earnings_data_webscraped.csv
HistoricalEarningsData/data/aggregated_earnings_data_with_iv.csv
HistoricalEarningsData-0.3.dist-info/METADATA
HistoricalEarningsData-0.3.dist-info/WHEEL
HistoricalEarningsData-0.3.dist-info/top_level.txt
HistoricalEarningsData-0.3.dist-info/RECORD
