Metadata-Version: 2.1
Name: HistoricalEarningsData
Version: 0.3
Summary: A package to query historical earnings report dates for stock tickers with implied volatility
Home-page: https://github.com/yourusername/historical_earnings_package
Author: Your Name
Author-email: your.email@example.com
License: UNKNOWN
Platform: UNKNOWN
Classifier: Programming Language :: Python :: 3
Classifier: License :: OSI Approved :: MIT License
Classifier: Operating System :: OS Independent
Requires-Python: >=3.6
Requires-Dist: pandas
